gq_sdk/__init__.py
gq_sdk/_helpers.py
gq_sdk/_http_manager.py
gq_sdk/_v5_auth.py
gq_sdk/_v5_credentials.py
gq_sdk/_v5_exchange.py
gq_sdk/_v5_limit_edge.py
gq_sdk/_v5_market_edge.py
gq_sdk/_v5_twap_edge.py
gq_sdk/_websocket_manager.py
gq_sdk/auth.py
gq_sdk/credentials.py
gq_sdk/exceptions.py
gq_sdk/exchange.py
gq_sdk/trade.py
gq_sdk/unified_trading.py
gq_sdk-0.1.3.dist-info/METADATA
gq_sdk-0.1.3.dist-info/WHEEL
gq_sdk-0.1.3.dist-info/licenses/LICENSE
gq_sdk-0.1.3.dist-info/RECORD
